pymemcache_client/__init__.py
pymemcache_client/pymemcache_client.py
pymemcache_client-0.3.2.dist-info/DESCRIPTION.rst
pymemcache_client-0.3.2.dist-info/METADATA
pymemcache_client-0.3.2.dist-info/RECORD
pymemcache_client-0.3.2.dist-info/WHEEL
pymemcache_client-0.3.2.dist-info/metadata.json
pymemcache_client-0.3.2.dist-info/top_level.txt
