Metadata-Version: 2.0
Name: pymemcache-client
Version: 0.3.2
Summary: Extension of Python package pymemcache providing client configuration through pymemcache.json.
Home-page: https://github.com/TuneLab/pymemcache-client
Author: TUNE Inc.
Author-email: jefft@tune.com
License: MIT License
Download-URL: https://github.com/TuneLab/pymemcache-client/archive/v0.3.2.tar.gz
Keywords: pymemcache client tune
Platform: UNKNOWN
Classifier: Development Status :: 3 - Alpha
Classifier: Intended Audience :: Developers
Classifier: Operating System :: OS Independent
Classifier: Natural Language :: English
Classifier: License :: OSI Approved :: MIT License
Classifier: Programming Language :: Python
Classifier: Programming Language :: Python :: 2.7
Classifier: Programming Language :: Python :: 3
Classifier: Programming Language :: Python :: 3.5
Classifier: Programming Language :: Python :: 3.6
Classifier: Programming Language :: Python :: Implementation :: PyPy
Requires-Dist: pprintpp (>=0.3.0)
Requires-Dist: pymemcache (>=1.4.3)
Requires-Dist: pytest (>=3.3.1)
Requires-Dist: pytest-mock (>=1.6.3)
Requires-Dist: pytest-cov (>=2.5.1)
Requires-Dist: telnetlib3 (>=1.0.0)
Requires-Dist: ujson (>=1.35)
Requires-Dist: wheel (>=0.30.0)
